qoffee/__init__.py
qoffee-0.0.1.dist-info/METADATA
qoffee-0.0.1.dist-info/WHEEL
qoffee-0.0.1.dist-info/top_level.txt
qoffee-0.0.1.dist-info/RECORD
