Metadata-Version: 2.4
Name: qoffee
Version: 0.0.1
Summary: QOFFEE — Quadratic Optimisation Fused with Feature Extraction and Elimination
Author-email: YOUR NAME <you@example.com>
License: MIT
Requires-Python: >=3.9
